[{"type": "e-header", "data": {"title": "*#friends_0#*", "picture": null, "sub_title": "*#friends_1#*", "description": null, "style": null, "btn": null}}, {"type": "e-card", "data": {"title": "*#friends_2#*", "picture": "https://static1.keepcdns.com/2018/09/25/1537870638253_1136x420.png", "sub_title": "*#friends_3#*", "description": "*#friends_4#*", "style": null, "btn": {"cname": "fill", "url": "http://show.keepkeep.com", "text": "*#friends_5#*", "style": null}}}, {"type": "e-btn", "data": {"title": null, "picture": null, "sub_title": null, "description": null, "style": null, "btn": {"cname": "line", "url": "http://show.keepkeep.com", "text": "*#friends_6#*", "style": "margin-top:2rem;margin-bottom:5.2rem;"}}}, {"type": "e-footer", "data": {"title": null, "picture": null, "sub_title": null, "description": null, "btn": null, "style": null}}]